source/sum_unit.v
/* 
    using the propagate signal P and the carry signal carry
    this module generates the sum signal Simulation
*/

module sum_unit #(parameter N = 8, D = 1) (P, C, S);

    // N is the bitwidth of our sum sum_unit
    // D is the delay of our sum_unit

    // I/O declaration 
    input [N-1:0] P, C;
    output [N-1:0] S;

    //not internal wiring at the level of abstraction in which this module is writen 

    // logic: S = P ^ C
    assign #(D) S = P ^ C;


endmodule

tb/sum_unit_tb.v
`timescale 1ns/1ns

//imports
`include "./source/sum_unit.v"

module sum_unit_tb;

    //setting parameters
    parameter N = 4;
    parameter D = 1;

    // I/O declaration
    reg [N-1:0] P = 0, C = 0;
    wire [N-1:0] S;

    //no additional testing variables are needed

    //intantiating the design under test
    sum_unit #(.N(N), .D(D)) dut (.P(P), .C(C), .S(S));_

    //test case generation and output verification 
    initial begin 

        $dumpfile("./waveforms/sum_unit_tb.vcd"); //waveform dumpfile
        $dumpvars(0, sum_unit_tb);

        repeat (2**(2*N)) begin
            #D;
            {P,C} += 1;
        end

        $display("Simulation Done");
        $finish;

    end

endmodule

waveforms/sum_unit_tb.vcd
$date
	Sun Feb 15 20:31:02 2026
$end
$version
	Icarus Verilog
$end
$timescale
	1ns
$end
$scope module sum_unit_tb $end
$var wire 4 ! S [3:0] $end
$var parameter 32 " D $end
$var parameter 32 # N $end
$var reg 4 $ C [3:0] $end
$var reg 4 % P [3:0] $end
$scope module dut $end
$var wire 4 & C [3:0] $end
$var wire 4 ' P [3:0] $end
$var wire 4 ( S [3:0] $end
$var parameter 32 ) D $end
$var parameter 32 * N $end
$upscope $end
$upscope $end
$enddefinitions $end
$comment Show the parameter values. $end
$dumpall
b100 *
b1 )
b100 #
b1 "
$end
#0
$dumpvars
bx (
b0 '
b0 &
b0 %
b0 $
bx !
$end
#1
b0 !
b0 (
b1 $
b1 &
#2
b1 !
b1 (
b10 $
b10 &
#3
b10 !
b10 (
b11 $
b11 &
#4
b11 !
b11 (
b100 $
b100 &
#5
b100 !
b100 (
b101 $
b101 &
#6
b101 !
b101 (
b110 $
b110 &
#7
b110 !
b110 (
b111 $
b111 &
#8
b111 !
b111 (
b1000 $
b1000 &
#9
b1000 !
b1000 (
b1001 $
b1001 &
#10
b1001 !
b1001 (
b1010 $
b1010 &
#11
b1010 !
b1010 (
b1011 $
b1011 &
#12
b1011 !
b1011 (
b1100 $
b1100 &
#13
b1100 !
b1100 (
b1101 $
b1101 &
#14
b1101 !
b1101 (
b1110 $
b1110 &
#15
b1110 !
b1110 (
b1111 $
b1111 &
#16
b1111 !
b1111 (
b1 %
b1 '
b0 $
b0 &
#17
b1 !
b1 (
b1 $
b1 &
#18
b0 !
b0 (
b10 $
b10 &
#19
b11 !
b11 (
b11 $
b11 &
#20
b10 !
b10 (
b100 $
b100 &
#21
b101 !
b101 (
b101 $
b101 &
#22
b100 !
b100 (
b110 $
b110 &
#23
b111 !
b111 (
b111 $
b111 &
#24
b110 !
b110 (
b1000 $
b1000 &
#25
b1001 !
b1001 (
b1001 $
b1001 &
#26
b1000 !
b1000 (
b1010 $
b1010 &
#27
b1011 !
b1011 (
b1011 $
b1011 &
#28
b1010 !
b1010 (
b1100 $
b1100 &
#29
b1101 !
b1101 (
b1101 $
b1101 &
#30
b1100 !
b1100 (
b1110 $
b1110 &
#31
b1111 !
b1111 (
b1111 $
b1111 &
#32
b1110 !
b1110 (
b10 %
b10 '
b0 $
b0 &
#33
b10 !
b10 (
b1 $
b1 &
#34
b11 !
b11 (
b10 $
b10 &
#35
b0 !
b0 (
b11 $
b11 &
#36
b1 !
b1 (
b100 $
b100 &
#37
b110 !
b110 (
b101 $
b101 &
#38
b111 !
b111 (
b110 $
b110 &
#39
b100 !
b100 (
b111 $
b111 &
#40
b101 !
b101 (
b1000 $
b1000 &
#41
b1010 !
b1010 (
b1001 $
b1001 &
#42
b1011 !
b1011 (
b1010 $
b1010 &
#43
b1000 !
b1000 (
b1011 $
b1011 &
#44
b1001 !
b1001 (
b1100 $
b1100 &
#45
b1110 !
b1110 (
b1101 $
b1101 &
#46
b1111 !
b1111 (
b1110 $
b1110 &
#47
b1100 !
b1100 (
b1111 $
b1111 &
#48
b1101 !
b1101 (
b11 %
b11 '
b0 $
b0 &
#49
b11 !
b11 (
b1 $
b1 &
#50
b10 !
b10 (
b10 $
b10 &
#51
b1 !
b1 (
b11 $
b11 &
#52
b0 !
b0 (
b100 $
b100 &
#53
b111 !
b111 (
b101 $
b101 &
#54
b110 !
b110 (
b110 $
b110 &
#55
b101 !
b101 (
b111 $
b111 &
#56
b100 !
b100 (
b1000 $
b1000 &
#57
b1011 !
b1011 (
b1001 $
b1001 &
#58
b1010 !
b1010 (
b1010 $
b1010 &
#59
b1001 !
b1001 (
b1011 $
b1011 &
#60
b1000 !
b1000 (
b1100 $
b1100 &
#61
b1111 !
b1111 (
b1101 $
b1101 &
#62
b1110 !
b1110 (
b1110 $
b1110 &
#63
b1101 !
b1101 (
b1111 $
b1111 &
#64
b1100 !
b1100 (
b100 %
b100 '
b0 $
b0 &
#65
b100 !
b100 (
b1 $
b1 &
#66
b101 !
b101 (
b10 $
b10 &
#67
b110 !
b110 (
b11 $
b11 &
#68
b111 !
b111 (
b100 $
b100 &
#69
b0 !
b0 (
b101 $
b101 &
#70
b1 !
b1 (
b110 $
b110 &
#71
b10 !
b10 (
b111 $
b111 &
#72
b11 !
b11 (
b1000 $
b1000 &
#73
b1100 !
b1100 (
b1001 $
b1001 &
#74
b1101 !
b1101 (
b1010 $
b1010 &
#75
b1110 !
b1110 (
b1011 $
b1011 &
#76
b1111 !
b1111 (
b1100 $
b1100 &
#77
b1000 !
b1000 (
b1101 $
b1101 &
#78
b1001 !
b1001 (
b1110 $
b1110 &
#79
b1010 !
b1010 (
b1111 $
b1111 &
#80
b1011 !
b1011 (
b101 %
b101 '
b0 $
b0 &
#81
b101 !
b101 (
b1 $
b1 &
#82
b100 !
b100 (
b10 $
b10 &
#83
b111 !
b111 (
b11 $
b11 &
#84
b110 !
b110 (
b100 $
b100 &
#85
b1 !
b1 (
b101 $
b101 &
#86
b0 !
b0 (
b110 $
b110 &
#87
b11 !
b11 (
b111 $
b111 &
#88
b10 !
b10 (
b1000 $
b1000 &
#89
b1101 !
b1101 (
b1001 $
b1001 &
#90
b1100 !
b1100 (
b1010 $
b1010 &
#91
b1111 !
b1111 (
b1011 $
b1011 &
#92
b1110 !
b1110 (
b1100 $
b1100 &
#93
b1001 !
b1001 (
b1101 $
b1101 &
#94
b1000 !
b1000 (
b1110 $
b1110 &
#95
b1011 !
b1011 (
b1111 $
b1111 &
#96
b1010 !
b1010 (
b110 %
b110 '
b0 $
b0 &
#97
b110 !
b110 (
b1 $
b1 &
#98
b111 !
b111 (
b10 $
b10 &
#99
b100 !
b100 (
b11 $
b11 &
#100
b101 !
b101 (
b100 $
b100 &
#101
b10 !
b10 (
b101 $
b101 &
#102
b11 !
b11 (
b110 $
b110 &
#103
b0 !
b0 (
b111 $
b111 &
#104
b1 !
b1 (
b1000 $
b1000 &
#105
b1110 !
b1110 (
b1001 $
b1001 &
#106
b1111 !
b1111 (
b1010 $
b1010 &
#107
b1100 !
b1100 (
b1011 $
b1011 &
#108
b1101 !
b1101 (
b1100 $
b1100 &
#109
b1010 !
b1010 (
b1101 $
b1101 &
#110
b1011 !
b1011 (
b1110 $
b1110 &
#111
b1000 !
b1000 (
b1111 $
b1111 &
#112
b1001 !
b1001 (
b111 %
b111 '
b0 $
b0 &
#113
b111 !
b111 (
b1 $
b1 &
#114
b110 !
b110 (
b10 $
b10 &
#115
b101 !
b101 (
b11 $
b11 &
#116
b100 !
b100 (
b100 $
b100 &
#117
b11 !
b11 (
b101 $
b101 &
#118
b10 !
b10 (
b110 $
b110 &
#119
b1 !
b1 (
b111 $
b111 &
#120
b0 !
b0 (
b1000 $
b1000 &
#121
b1111 !
b1111 (
b1001 $
b1001 &
#122
b1110 !
b1110 (
b1010 $
b1010 &
#123
b1101 !
b1101 (
b1011 $
b1011 &
#124
b1100 !
b1100 (
b1100 $
b1100 &
#125
b1011 !
b1011 (
b1101 $
b1101 &
#126
b1010 !
b1010 (
b1110 $
b1110 &
#127
b1001 !
b1001 (
b1111 $
b1111 &
#128
b1000 !
b1000 (
b1000 %
b1000 '
b0 $
b0 &
#129
b1 $
b1 &
#130
b1001 !
b1001 (
b10 $
b10 &
#131
b1010 !
b1010 (
b11 $
b11 &
#132
b1011 !
b1011 (
b100 $
b100 &
#133
b1100 !
b1100 (
b101 $
b101 &
#134
b1101 !
b1101 (
b110 $
b110 &
#135
b1110 !
b1110 (
b111 $
b111 &
#136
b1111 !
b1111 (
b1000 $
b1000 &
#137
b0 !
b0 (
b1001 $
b1001 &
#138
b1 !
b1 (
b1010 $
b1010 &
#139
b10 !
b10 (
b1011 $
b1011 &
#140
b11 !
b11 (
b1100 $
b1100 &
#141
b100 !
b100 (
b1101 $
b1101 &
#142
b101 !
b101 (
b1110 $
b1110 &
#143
b110 !
b110 (
b1111 $
b1111 &
#144
b111 !
b111 (
b1001 %
b1001 '
b0 $
b0 &
#145
b1001 !
b1001 (
b1 $
b1 &
#146
b1000 !
b1000 (
b10 $
b10 &
#147
b1011 !
b1011 (
b11 $
b11 &
#148
b1010 !
b1010 (
b100 $
b100 &
#149
b1101 !
b1101 (
b101 $
b101 &
#150
b1100 !
b1100 (
b110 $
b110 &
#151
b1111 !
b1111 (
b111 $
b111 &
#152
b1110 !
b1110 (
b1000 $
b1000 &
#153
b1 !
b1 (
b1001 $
b1001 &
#154
b0 !
b0 (
b1010 $
b1010 &
#155
b11 !
b11 (
b1011 $
b1011 &
#156
b10 !
b10 (
b1100 $
b1100 &
#157
b101 !
b101 (
b1101 $
b1101 &
#158
b100 !
b100 (
b1110 $
b1110 &
#159
b111 !
b111 (
b1111 $
b1111 &
#160
b110 !
b110 (
b1010 %
b1010 '
b0 $
b0 &
#161
b1010 !
b1010 (
b1 $
b1 &
#162
b1011 !
b1011 (
b10 $
b10 &
#163
b1000 !
b1000 (
b11 $
b11 &
#164
b1001 !
b1001 (
b100 $
b100 &
#165
b1110 !
b1110 (
b101 $
b101 &
#166
b1111 !
b1111 (
b110 $
b110 &
#167
b1100 !
b1100 (
b111 $
b111 &
#168
b1101 !
b1101 (
b1000 $
b1000 &
#169
b10 !
b10 (
b1001 $
b1001 &
#170
b11 !
b11 (
b1010 $
b1010 &
#171
b0 !
b0 (
b1011 $
b1011 &
#172
b1 !
b1 (
b1100 $
b1100 &
#173
b110 !
b110 (
b1101 $
b1101 &
#174
b111 !
b111 (
b1110 $
b1110 &
#175
b100 !
b100 (
b1111 $
b1111 &
#176
b101 !
b101 (
b1011 %
b1011 '
b0 $
b0 &
#177
b1011 !
b1011 (
b1 $
b1 &
#178
b1010 !
b1010 (
b10 $
b10 &
#179
b1001 !
b1001 (
b11 $
b11 &
#180
b1000 !
b1000 (
b100 $
b100 &
#181
b1111 !
b1111 (
b101 $
b101 &
#182
b1110 !
b1110 (
b110 $
b110 &
#183
b1101 !
b1101 (
b111 $
b111 &
#184
b1100 !
b1100 (
b1000 $
b1000 &
#185
b11 !
b11 (
b1001 $
b1001 &
#186
b10 !
b10 (
b1010 $
b1010 &
#187
b1 !
b1 (
b1011 $
b1011 &
#188
b0 !
b0 (
b1100 $
b1100 &
#189
b111 !
b111 (
b1101 $
b1101 &
#190
b110 !
b110 (
b1110 $
b1110 &
#191
b101 !
b101 (
b1111 $
b1111 &
#192
b100 !
b100 (
b1100 %
b1100 '
b0 $
b0 &
#193
b1100 !
b1100 (
b1 $
b1 &
#194
b1101 !
b1101 (
b10 $
b10 &
#195
b1110 !
b1110 (
b11 $
b11 &
#196
b1111 !
b1111 (
b100 $
b100 &
#197
b1000 !
b1000 (
b101 $
b101 &
#198
b1001 !
b1001 (
b110 $
b110 &
#199
b1010 !
b1010 (
b111 $
b111 &
#200
b1011 !
b1011 (
b1000 $
b1000 &
#201
b100 !
b100 (
b1001 $
b1001 &
#202
b101 !
b101 (
b1010 $
b1010 &
#203
b110 !
b110 (
b1011 $
b1011 &
#204
b111 !
b111 (
b1100 $
b1100 &
#205
b0 !
b0 (
b1101 $
b1101 &
#206
b1 !
b1 (
b1110 $
b1110 &
#207
b10 !
b10 (
b1111 $
b1111 &
#208
b11 !
b11 (
b1101 %
b1101 '
b0 $
b0 &
#209
b1101 !
b1101 (
b1 $
b1 &
#210
b1100 !
b1100 (
b10 $
b10 &
#211
b1111 !
b1111 (
b11 $
b11 &
#212
b1110 !
b1110 (
b100 $
b100 &
#213
b1001 !
b1001 (
b101 $
b101 &
#214
b1000 !
b1000 (
b110 $
b110 &
#215
b1011 !
b1011 (
b111 $
b111 &
#216
b1010 !
b1010 (
b1000 $
b1000 &
#217
b101 !
b101 (
b1001 $
b1001 &
#218
b100 !
b100 (
b1010 $
b1010 &
#219
b111 !
b111 (
b1011 $
b1011 &
#220
b110 !
b110 (
b1100 $
b1100 &
#221
b1 !
b1 (
b1101 $
b1101 &
#222
b0 !
b0 (
b1110 $
b1110 &
#223
b11 !
b11 (
b1111 $
b1111 &
#224
b10 !
b10 (
b1110 %
b1110 '
b0 $
b0 &
#225
b1110 !
b1110 (
b1 $
b1 &
#226
b1111 !
b1111 (
b10 $
b10 &
#227
b1100 !
b1100 (
b11 $
b11 &
#228
b1101 !
b1101 (
b100 $
b100 &
#229
b1010 !
b1010 (
b101 $
b101 &
#230
b1011 !
b1011 (
b110 $
b110 &
#231
b1000 !
b1000 (
b111 $
b111 &
#232
b1001 !
b1001 (
b1000 $
b1000 &
#233
b110 !
b110 (
b1001 $
b1001 &
#234
b111 !
b111 (
b1010 $
b1010 &
#235
b100 !
b100 (
b1011 $
b1011 &
#236
b101 !
b101 (
b1100 $
b1100 &
#237
b10 !
b10 (
b1101 $
b1101 &
#238
b11 !
b11 (
b1110 $
b1110 &
#239
b0 !
b0 (
b1111 $
b1111 &
#240
b1 !
b1 (
b1111 %
b1111 '
b0 $
b0 &
#241
b1111 !
b1111 (
b1 $
b1 &
#242
b1110 !
b1110 (
b10 $
b10 &
#243
b1101 !
b1101 (
b11 $
b11 &
#244
b1100 !
b1100 (
b100 $
b100 &
#245
b1011 !
b1011 (
b101 $
b101 &
#246
b1010 !
b1010 (
b110 $
b110 &
#247
b1001 !
b1001 (
b111 $
b111 &
#248
b1000 !
b1000 (
b1000 $
b1000 &
#249
b111 !
b111 (
b1001 $
b1001 &
#250
b110 !
b110 (
b1010 $
b1010 &
#251
b101 !
b101 (
b1011 $
b1011 &
#252
b100 !
b100 (
b1100 $
b1100 &
#253
b11 !
b11 (
b1101 $
b1101 &
#254
b10 !
b10 (
b1110 $
b1110 &
#255
b1 !
b1 (
b1111 $
b1111 &
#256
b0 !
b0 (
b0 %
b0 '
b0 $
b0 &
