source/up_counter.v
module up_counter(input clk, input [3:0] val, input load, output R);
    reg [3:0] state = 4'd0;

    always @(posedge clk) begin
        if (load) begin 
            state <= load;
        end else begin 
            state <= state + 4'd1;
        end 
    end

    assign R = state[3] & state[2] & state[1] & state[0];
endmodule

tb/up_counter_tb.v
`timescale 1ns/1ns
`include "source/up_counter.v"

module up_counter_tb;
    reg clk = 1;
    wire R;
    reg [3:0] val;
    reg load;
    up_counter dut(clk, val, load, R);
    always #(1) clk = ~clk;

    initial begin   
        $dumpfile("up_counter_tb.vcd");
        $dumpvars(0, up_counter_tb);

        #(32);
        val = 4'd7;
        load = 1;
        #(2)
        load = 0;
        #(14);

        $display("simulation done");
        $finish;
    end
endmodule

waveforms/up_counter_tb.vcd
$date
	Thu Feb 19 14:28:19 2026
$end
$version
	Icarus Verilog
$end
$timescale
	1ns
$end
$scope module up_counter_tb $end
$var wire 1 ! R $end
$var reg 1 " clk $end
$var reg 1 # load $end
$var reg 4 $ val [3:0] $end
$scope module dut $end
$var wire 1 ! R $end
$var wire 1 " clk $end
$var wire 1 # load $end
$var wire 4 % val [3:0] $end
$var reg 4 & state [3:0] $end
$upscope $end
$upscope $end
$enddefinitions $end
$comment Show the parameter values. $end
$dumpall
$end
#0
$dumpvars
b0 &
bx %
bx $
x#
1"
0!
$end
#1
0"
#2
b1 &
1"
#3
0"
#4
b10 &
1"
#5
0"
#6
b11 &
1"
#7
0"
#8
b100 &
1"
#9
0"
#10
b101 &
1"
#11
0"
#12
b110 &
1"
#13
0"
#14
b111 &
1"
#15
0"
#16
b1000 &
1"
#17
0"
#18
b1001 &
1"
#19
0"
#20
b1010 &
1"
#21
0"
#22
b1011 &
1"
#23
0"
#24
b1100 &
1"
#25
0"
#26
b1101 &
1"
#27
0"
#28
b1110 &
1"
#29
0"
#30
1!
b1111 &
1"
#31
0"
#32
0!
b1 &
1"
1#
b111 $
b111 %
#33
0"
#34
b10 &
1"
0#
#35
0"
#36
b11 &
1"
#37
0"
#38
b100 &
1"
#39
0"
#40
b101 &
1"
#41
0"
#42
b110 &
1"
#43
0"
#44
b111 &
1"
#45
0"
#46
b1000 &
1"
#47
0"
#48
b1001 &
1"
