part_sims/FA/FA.v
module FA( // adder bitslice
    input a,b, Cin,
    output Cout, P, S);
    parameter nand_d = 1, xor_d = 1; 

    wire nab, naCin, nbCin;
    xor #(xor_d) x0 (P, a, b);
    xor #(xor_d) x1 (S, P, Cin);
    nand #(nand_d) n1 (nab, a, b);
    nand #(nand_d) n2 (naCin, a, Cin);
    nand #(nand_d) n3 (nbCin, b, Cin);
    nand #(nand_d) n4 (Cout, nab, naCin, nbCin);

endmodule

part_sims/FA/FA_tb.v
`timescale 1ns/1ns
//neccesary imports
`include "FA.v" 

module FA_tb;

	reg a = 0, b = 0, Cin = 0; //input declaration
	wire Cout, P, S; //output declaration

	wire [1:0] expected;
	assign expected = a + b + Cin;

	//design under test
	FA dut(.a(a), .b(b), .Cin(Cin), .Cout(Cout), .P(P), .S(S));

	initial begin

		$dumpfile("FA_tb.vcd"); //where to dump waveform
		$dumpvars(0, FA_tb);    

		repeat (8) begin 
			#3; 
			if ({Cout, S} != expected) begin //output testing
				$display("Error: a=%b b=%b Cin=%b | Expected=%b Got=%b", a, b, Cin, expected, {Cout,S});
			end
			{a, b, Cin} += 1; //input case generation
		end

		$display("Simulation Complete"); //just to check that the program counter gets to this
		$finish; //return control back to the OS ??? 

	end   

endmodule

part_sims/FA/FA_tb.vcd
$date
	Sun Feb  8 22:58:28 2026
$end
$version
	Icarus Verilog
$end
$timescale
	1ns
$end
$scope module FA_tb $end
$var wire 2 ! expected [1:0] $end
$var wire 1 " S $end
$var wire 1 # P $end
$var wire 1 $ Cout $end
$var reg 1 % Cin $end
$var reg 1 & a $end
$var reg 1 ' b $end
$scope module dut $end
$var wire 1 % Cin $end
$var wire 1 $ Cout $end
$var wire 1 # P $end
$var wire 1 " S $end
$var wire 1 & a $end
$var wire 1 ' b $end
$var wire 1 ( naCin $end
$var wire 1 ) nab $end
$var wire 1 * nbCin $end
$var parameter 32 + nand_d $end
$var parameter 32 , xor_d $end
$upscope $end
$upscope $end
$enddefinitions $end
$comment Show the parameter values. $end
$dumpall
b1 ,
b1 +
$end
#0
$dumpvars
x*
x)
x(
0'
0&
0%
x$
x#
x"
b0 !
$end
#1
0#
1)
1(
1*
#2
0"
0$
#3
b1 !
1%
#4
1"
#6
b1 !
1'
0%
#7
1#
0"
#8
1"
#9
b10 !
1%
#10
0"
0*
#11
1$
#12
b1 !
1&
0'
0%
#13
1"
1*
#14
0$
#15
b10 !
1%
#16
0"
0(
#17
1$
#18
b10 !
1'
0%
#19
0#
0)
1"
1(
#20
0"
#21
b11 !
1%
#22
1"
0(
0*
#24
b0 !
0&
0'
0%
