RCA/FA.v
// this is a 1 bit Full Adder
module FA #(parameter NAND_D = 1, XOR_D = 1) (S, P, Cout, a, b, Cin);
    input a, b, Cin;
    output Cout, P, S;

    // carry unit
    wire nab, naCin, nbCin;
    nand #(NAND_D) nand_1_0 (nab, a, b);
    nand #(NAND_D) nand_1_1 (naCin, a, Cin);
    nand #(NAND_D) nand_1_2 (nbCin, b, Cin);
    nand #(NAND_D) nand_2_0 (Cout, nab, naCin, nbCin);

    // sum unit
    xor #(XOR_D) x0 (P, a, b);
    xor #(XOR_D) x1 (S, P, Cin);

endmodule

RCA/FA_tb.v
`timescale 1ns/1ns
//neccesary imports
`include "FA.v" 

module FA_tb;

	// I/O declaration
	reg a = 0, b = 0, Cin = 0; 
	wire Cout, P, S;

	wire [1:0] expected;
	assign expected = a + b + Cin;

	//design under test
	FA #(1,1) FA_2_1 (.a(a), .b(b), .Cin(Cin), .Cout(Cout), .P(P), .S(S));
	reg [1023:0] vcd_file;

	initial begin

		if ($test$plusargs("DUMP_ON")) begin

            $display("Waveform dumping enabled.");
			$value$plusargs("VCD_NAME=%s", vcd_file);
            $dumpfile(vcd_file); 
            $dumpvars(0, FA_tb);    
        end else begin
            $display("Note: Waveform dumping disabled.");
        end   

		repeat (8) begin 
			#3; 
			if ({Cout, S} !== expected) begin //output testing
				$display("Error: a=%b b=%b Cin=%b | Expected=%b Got=%b\n", a, b, Cin, expected, {Cout,S});
			end
			{a, b, Cin} += 1; //input case generation
		end

		$display("Simulation Complete"); //just to check that the program counter gets to this
		$finish; //return control back to the OS 

	end   

endmodule

RCA/FA_tb.vcd
$date
	Fri Mar 13 02:22:05 2026
$end
$version
	Icarus Verilog
$end
$timescale
	1ns
$end
$scope module FA_tb $end
$var wire 2 ! expected [1:0] $end
$var wire 1 " S $end
$var wire 1 # P $end
$var wire 1 $ Cout $end
$var reg 1 % Cin $end
$var reg 1 & a $end
$var reg 1 ' b $end
$var reg 1024 ( vcd_file [1023:0] $end
$scope module FA_2_1 $end
$var wire 1 % Cin $end
$var wire 1 $ Cout $end
$var wire 1 # P $end
$var wire 1 " S $end
$var wire 1 & a $end
$var wire 1 ' b $end
$var wire 1 ) naCin $end
$var wire 1 * nab $end
$var wire 1 + nbCin $end
$var parameter 32 , NAND_D $end
$var parameter 32 - XOR_D $end
$upscope $end
$upscope $end
$enddefinitions $end
$comment Show the parameter values. $end
$dumpall
b1 -
b1 ,
$end
#0
$dumpvars
x+
x*
x)
b10001100100000101011111011101000110001000101110011101100110001101100100 (
0'
0&
0%
x$
x#
x"
b0 !
$end
#1
0#
1*
1)
1+
#2
0"
0$
#3
b1 !
1%
#4
1"
#6
b1 !
1'
0%
#7
1#
0"
#8
1"
#9
b10 !
1%
#10
0+
0"
#11
1$
#12
b1 !
1&
0'
0%
#13
1+
1"
#14
0$
#15
b10 !
1%
#16
0)
0"
#17
1$
#18
b10 !
1'
0%
#19
0*
0#
1)
1"
#20
0"
#21
b11 !
1%
#22
0)
0+
1"
#24
b0 !
0&
0'
0%
