iverilog_examples/up_counter/up_counter_synth.v
/* Generated by Yosys 0.61+129 (git sha1 6dbe03f0f-dirty, aarch64-apple-darwin23.5-clang++ 18.1.8 -fPIC -O3) */

(* top =  1  *)
(* src = "up_counter.v:1.1-11.10" *)
module up_counter(clk, R);
  (* src = "up_counter.v:2.11-2.14" *)
  input clk;
  wire clk;
  (* src = "up_counter.v:4.12-4.13" *)
  output R;
  wire R;
  (* src = "up_counter.v:10.16-10.35" *)
  wire _00_;
  (* src = "up_counter.v:10.16-10.46" *)
  wire _01_;
  (* force_downto = 32'd1 *)
  (* src = "up_counter.v:7.18-7.30|/Users/adityaln/Applications/oss-cad-suite/libexec/../share/yosys/techmap.v:274.23-274.25" *)
  (* unused_bits = "3" *)
  wire [7:0] _02_;
  (* force_downto = 32'd1 *)
  (* src = "up_counter.v:7.18-7.30|/Users/adityaln/Applications/oss-cad-suite/libexec/../share/yosys/techmap.v:287.21-287.22" *)
  wire [7:0] _03_;
  (* force_downto = 32'd1 *)
  (* src = "up_counter.v:7.18-7.30|/Users/adityaln/Applications/oss-cad-suite/libexec/../share/yosys/techmap.v:270.26-270.27" *)
  (* unused_bits = "4" *)
  wire [7:0] _04_;
  (* src = "up_counter.v:3.15-3.20" *)
  reg [3:0] state = 4'h0;
  (* src = "up_counter.v:6.5-8.8" *)
  always @(posedge clk)
    state[0] <= _03_[0];
  (* src = "up_counter.v:6.5-8.8" *)
  always @(posedge clk)
    state[1] <= _04_[1];
  (* src = "up_counter.v:6.5-8.8" *)
  always @(posedge clk)
    state[2] <= _04_[2];
  (* src = "up_counter.v:6.5-8.8" *)
  always @(posedge clk)
    state[3] <= _04_[3];
  assign _03_[0] = ~state[0];
  assign _02_[1] = state[1] &(* src = "up_counter.v:7.18-7.30|/Users/adityaln/Applications/oss-cad-suite/libexec/../share/yosys/techmap.v:293.27-293.63|/Users/adityaln/Applications/oss-cad-suite/libexec/../share/yosys/techmap.v:240.19-240.41" *)  state[0];
  assign _00_ = state[3] &(* src = "up_counter.v:7.18-7.30|/Users/adityaln/Applications/oss-cad-suite/libexec/../share/yosys/techmap.v:293.27-293.63|/Users/adityaln/Applications/oss-cad-suite/libexec/../share/yosys/techmap.v:241.12-241.34" *)  state[2];
  assign _02_[2] = state[2] &(* src = "up_counter.v:7.18-7.30|/Users/adityaln/Applications/oss-cad-suite/libexec/../share/yosys/techmap.v:293.27-293.63|/Users/adityaln/Applications/oss-cad-suite/libexec/../share/yosys/techmap.v:248.19-248.41" *)  _02_[1];
  assign _01_ = _00_ &(* src = "up_counter.v:10.16-10.46" *)  state[1];
  assign R = _01_ &(* src = "up_counter.v:10.16-10.57" *)  state[0];
  assign _04_[1] = state[1] ^(* src = "up_counter.v:7.18-7.30|/Users/adityaln/Applications/oss-cad-suite/libexec/../share/yosys/techmap.v:296.13-296.25" *)  state[0];
  assign _04_[2] = state[2] ^(* src = "up_counter.v:7.18-7.30|/Users/adityaln/Applications/oss-cad-suite/libexec/../share/yosys/techmap.v:296.13-296.25" *)  _02_[1];
  assign _04_[3] = state[3] ^(* src = "up_counter.v:7.18-7.30|/Users/adityaln/Applications/oss-cad-suite/libexec/../share/yosys/techmap.v:296.13-296.25" *)  _02_[2];
  assign { _02_[7:4], _02_[0] } = { 4'h0, state[0] };
  assign _03_[7:1] = { 4'h0, state[3:1] };
  assign { _04_[7:4], _04_[0] } = { 3'h0, _02_[3], _03_[0] };
endmodule

iverilog_examples/up_counter/up_counter_tb.v
`timescale 1ns/1ns
`include "up_counter_synth.v"

module up_counter_tb;
    reg clk = 1;
    wire R;
    up_counter dut(clk, R);
    always #(1) clk = ~clk;

    initial begin   
        $dumpfile("up_counter_tb.vcd");
        $dumpvars(0, up_counter_tb);

        #(32);

        $display("simulation done");
        $finish;
    end
endmodule

iverilog_examples/up_counter/up_counter_tb.vcd
$date
	Thu Feb 12 23:40:27 2026
$end
$version
	Icarus Verilog
$end
$timescale
	1ns
$end
$scope module up_counter_tb $end
$var wire 1 ! R $end
$var reg 1 " clk $end
$scope module dut $end
$var wire 1 ! R $end
$var wire 1 # _00_ $end
$var wire 1 $ _01_ $end
$var wire 1 " clk $end
$var wire 8 % _04_ [7:0] $end
$var wire 8 & _03_ [7:0] $end
$var wire 8 ' _02_ [7:0] $end
$var reg 4 ( state [3:0] $end
$upscope $end
$upscope $end
$enddefinitions $end
$comment Show the parameter values. $end
$dumpall
$end
#0
$dumpvars
b0 (
b0z000 '
b1 &
b0z0001 %
0$
0#
1"
0!
$end
#1
0"
#2
b0z001 '
b0z0010 %
b0 &
b1 (
1"
#3
0"
#4
b0z0011 %
b0z000 '
b11 &
b10 (
1"
#5
0"
#6
b0z011 '
b0z0100 %
b10 &
b11 (
1"
#7
0"
#8
b0z0101 %
b0z000 '
b101 &
b100 (
1"
#9
0"
#10
b0z001 '
b0z0110 %
b100 &
b101 (
1"
#11
0"
#12
b0z0111 %
b0z000 '
b111 &
b110 (
1"
#13
0"
#14
b0z111 '
b0z1000 %
b110 &
b111 (
1"
#15
0"
#16
b0z1001 %
b0z000 '
b1001 &
b1000 (
1"
#17
0"
#18
b0z001 '
b0z1010 %
b1000 &
b1001 (
1"
#19
0"
#20
b0z1011 %
b0z000 '
b1011 &
b1010 (
1"
#21
0"
#22
b0z011 '
b0z1100 %
b1010 &
b1011 (
1"
#23
0"
#24
b0z1101 %
b0z000 '
b1101 &
1#
b1100 (
1"
#25
0"
#26
b0z001 '
b0z1110 %
b1100 &
b1101 (
1"
#27
0"
#28
b0z1111 %
b0z000 '
b1111 &
1$
b1110 (
1"
#29
0"
#30
b0z111 '
b0z0000 %
b1110 &
1!
b1111 (
1"
#31
0"
#32
b0z0001 %
b0z000 '
b1 &
0#
0$
0!
b0 (
1"
